{
    "name": "historical-dob-permit-issuance",
    "datapackage_version": "1.0-beta",
    "title": "Historical DOB Permit Issuance",
    "version": "N/A",
    "keywords": [
        "permits",
        "buildings",
        "dob"
    ],
    "description": "A list of permits issued for a particular day and associated data.\r\n\r\nA list of permits issued between May 11 1989 through April 24, 2013.",
    "licenses": [],
    "sources": [
        {
            "title": "Department of Buildings (DOB)"
        }
    ],
    "contributors": [],
    "maintainers": [],
    "publishers": [],
    "dependencies": {},
    "resources": [
        {
            "path": "data.csv",
            "url": "https://data.cityofnewyork.us/api/views/bty7-2jhb/rows.csv?accessType=DOWNLOAD"
        }
    ],
    "views": [],
    "rows": 2430000,
    "columns": 54,
    "filesize": null,
    "available_formats": null,
    "metadata": [],
    "complete": true,
    "page_views": 331,
    "preferred_mimetype": "text/csv",
    "topics_provided": [
        "Housing & Development"
    ],
    "preferred_format": "csv",
    "column_names": [
        "Permittee's First Name",
        "Owner's First Name",
        "Job Type",
        "Street Name",
        "House #",
        "Job #",
        "Bin #",
        "Self_Cert",
        "Permittee's Last Name",
        "BOROUGH",
        "HIC License",
        "Job doc. #",
        "Permittee's Other Title",
        "Oil Gas",
        "Permittee's Phone #",
        "Owner's Phone #",
        "DOBRunDate",
        "Permit Sequence #",
        "Permit Subtype",
        "Owner\u2019s House Zip Code",
        "Site Fill",
        "Site Safety Mgr's First Name",
        "Permit Status",
        "Owner's House #",
        "Site Safety Mgr's Last Name",
        "Permittee's License #",
        "Expiration Date",
        "Zip Code",
        "Bldg Type",
        "Residential",
        "Work Type",
        "Non-Profit",
        "Owner's Last Name",
        "Superintendent Business Name",
        "Act as Superintendent",
        "Owner's Business Name",
        "Site Safety Mgr Business Name",
        "Owner's House Street Name",
        "Block",
        "Owner\u2019s House State",
        "Special District 1",
        "Owner\u2019s House City",
        "Permittee's License Type",
        "Permittee's Business Name",
        "Special District 2",
        "Owner's Business Type",
        "Job Start Date",
        "Lot",
        "Filing Date",
        "Superintendent First & Last Name",
        "Community Board",
        "Filing Status",
        "Permit Type",
        "Issuance Date"
    ],
    "landing_page": "https://data.cityofnewyork.us/d/bty7-2jhb",
    "last_updated": "2017-05-23 15:52:23+00:00",
    "protocol": "https",
    "created": "2016-09-27 19:05:32+00:00"
}