{
    "name": "demographics-and-profiles-at-the-neighborhood-tabulation-area-nta-level",
    "datapackage_version": "1.0-beta",
    "title": "Demographics and profiles at the Neighborhood Tabulation Area (NTA) level",
    "version": "N/A",
    "keywords": [
        "acs",
        "pumas",
        "census",
        "nta"
    ],
    "description": "Table of ACS Demographics and\nprofile represented at the NTA level.\nNTAs are aggregations of census tracts\nthat are subsets of New York City's 55\nPublic Use Microdata Areas (PUMAs)",
    "licenses": [],
    "sources": [
        {
            "title": "Department of City Planning (DCP)"
        }
    ],
    "contributors": [],
    "maintainers": [],
    "publishers": [],
    "dependencies": {},
    "resources": [],
    "views": [],
    "rows": null,
    "columns": null,
    "filesize": 1026.638671875,
    "available_formats": null,
    "metadata": [],
    "complete": false,
    "page_views": 672,
    "preferred_mimetype": "application/vnd.openxmlformats-officedocument.spreadsheetml.sheet",
    "topics_provided": [
        "City Government"
    ],
    "preferred_format": "xlsx",
    "column_names": [],
    "landing_page": "https://data.cityofnewyork.us/d/hyuz-tij8",
    "last_updated": "2015-02-17 16:50:31+00:00",
    "protocol": "https",
    "created": "2015-02-17 16:49:14+00:00"
}