{
    "name": "ccrb-assignment-of-officers-against-whom-allegations-were-substantiated-patrol-borough-staten-island-2005-2009",
    "datapackage_version": "1.0-beta",
    "title": "CCRB: Assignment of Officers against Whom Allegations Were Substantiated - Patrol Borough Staten Island 2005 - 2009",
    "version": "N/A",
    "keywords": [
        "2005",
        "2007",
        "2006",
        "activity",
        "board",
        "ccrb",
        "civilian",
        "civilian complaint review board",
        "complaint",
        "review",
        "complaint activity",
        "statistics",
        "2009",
        "2008"
    ],
    "description": "Civilian Complaint Review Board (CCRB) complaint activity data, 2005-2009.\r\nUpdate Schedule: Annually",
    "licenses": [],
    "sources": [
        {
            "title": "Civilian Complaint Review Board (CCRB)"
        }
    ],
    "contributors": [],
    "maintainers": [],
    "publishers": [],
    "dependencies": {},
    "resources": [
        {
            "path": "data.csv",
            "url": "https://data.cityofnewyork.us/api/views/gd6m-k9v9/rows.csv?accessType=DOWNLOAD"
        }
    ],
    "views": [],
    "rows": 11,
    "columns": 7,
    "filesize": null,
    "available_formats": null,
    "metadata": [],
    "complete": true,
    "page_views": 101,
    "preferred_mimetype": "text/csv",
    "topics_provided": [
        "Public Safety"
    ],
    "preferred_format": "csv",
    "column_names": [
        "Staten Island",
        "2008",
        "2009",
        "2005",
        "Total",
        "2007",
        "2006"
    ],
    "landing_page": "https://data.cityofnewyork.us/d/gd6m-k9v9",
    "last_updated": "2014-09-05 16:57:42+00:00",
    "protocol": "https",
    "created": "2011-09-13 20:36:37+00:00"
}