{
    "name": "311-service-requests-for-2007",
    "datapackage_version": "1.0-beta",
    "title": "311 Service Requests for 2007",
    "version": "N/A",
    "keywords": [
        "2007",
        "311",
        "all service requests",
        "311 service requests"
    ],
    "description": "311 Service Requests for 2007. This is historical data and will not be updated.",
    "licenses": [],
    "sources": [
        {
            "title": "311"
        }
    ],
    "contributors": [],
    "maintainers": [],
    "publishers": [],
    "dependencies": {},
    "resources": [
        {
            "path": "data.csv",
            "url": "https://data.cityofnewyork.us/api/views/aiww-p3af/rows.csv?accessType=DOWNLOAD"
        }
    ],
    "views": [],
    "rows": 1880000,
    "columns": 52,
    "filesize": null,
    "available_formats": null,
    "metadata": [],
    "complete": true,
    "page_views": 583,
    "preferred_mimetype": "text/csv",
    "topics_provided": [
        "Social Services"
    ],
    "preferred_format": "csv",
    "column_names": [
        "Ferry Direction",
        "Road Ramp",
        "School Not Found",
        "School City",
        "Descriptor",
        "School State",
        "Park Borough",
        "Park Facility Name",
        "Y Coordinate (State Plane)",
        "X Coordinate (State Plane)",
        "School Number",
        "Longitude",
        "Taxi Pick Up Location",
        "School or Citywide Complaint",
        "Vehicle Type",
        "School Zip",
        "Location",
        "Address Type",
        "Latitude",
        "Incident Address",
        "Cross Street 1",
        "Street Name",
        "Intersection Street 1",
        "Cross Street 2",
        "Intersection Street 2",
        "Landmark",
        "City",
        "School Address",
        "School Phone Number",
        "School Code",
        "School Region",
        "School Name",
        "Bridge Highway Direction",
        "Bridge Highway Name",
        "Bridge Highway Segment",
        "Garage Lot Name",
        "Ferry Terminal Name",
        "Facility Type",
        "Status",
        "Due Date",
        "Resolution Action Updated Date",
        "Community Board",
        "Unique Key",
        "Incident Zip",
        "Created Date",
        "Taxi Company Borough",
        "Borough",
        "Agency",
        "Closed Date",
        "Complaint Type",
        "Agency Name",
        "Location Type"
    ],
    "landing_page": "https://data.cityofnewyork.us/d/aiww-p3af",
    "last_updated": "2017-02-03 18:59:58+00:00",
    "protocol": "https",
    "created": "2011-10-10 21:55:59+00:00"
}