{
    "name": "school-progress-reports-all-schools-2010-11",
    "datapackage_version": "1.0-beta",
    "title": "School Progress Reports - All Schools - 2010-11",
    "version": "N/A",
    "keywords": [
        "lifelong learning"
    ],
    "description": "2010/11 Progress Report results for all schools (As of 9/23/2011)\r\n\r\nPeer indexes are calculated differently depending on School Level.  Schools are only compared to other schools in the same School Level (e.g., Elementary, K-8, Middle, High, Transfer)\r\n\r\n1) Elementary, K-8, Early Childhood - peer index is a value from 0-100.  A composite demographic statistic based on % ELL, % Students with Disabilities, % Title I free lunch, and % Black/Hispanic is used.  Higher values indicate student populations with higher need.\r\n\r\n2) Middle - peer index is a value from 1.00-4.50.  For middle schools, the average 4th grade proficiency ratings in ELA and Math and the % Students with Disabilities is used. Lower values indicate student populations with higher need.\r\n\r\n3) High School - peer index is a value from 1.00-4.50. For high schools, the average 8th grade proficiency, the % Students with Disabilities, the % Self-contained, and the % overage is used. Lower values indicate student populations with higher need.",
    "licenses": [],
    "sources": [
        {
            "title": "Department of Education (DOE)"
        }
    ],
    "contributors": [],
    "maintainers": [],
    "publishers": [],
    "dependencies": {},
    "resources": [
        {
            "path": "data.csv",
            "url": "https://data.cityofnewyork.us/api/views/yig9-9zum/rows.csv?accessType=DOWNLOAD"
        }
    ],
    "views": [],
    "rows": 1219,
    "columns": 17,
    "filesize": null,
    "available_formats": null,
    "metadata": [],
    "complete": true,
    "page_views": 1240,
    "preferred_mimetype": "text/csv",
    "topics_provided": [
        "Education"
    ],
    "preferred_format": "csv",
    "column_names": [
        "SCHOOL LEVEL*",
        "2010-2011 PERFORMANCE GRADE",
        "DBN",
        "DISTRICT",
        "2010-2011 ADDITIONAL CREDIT",
        "2010-2011 PROGRESS GRADE",
        "2009-10 PROGRESS REPORT GRADE",
        "PEER INDEX*",
        "PROGRESS REPORT TYPE",
        "2010-2011 OVERALL GRADE",
        "2010-2011 PROGRESS CATEGORY SCORE",
        "2010-2011 OVERALL SCORE",
        "2010-2011 ENVIRONMENT CATEGORY SCORE",
        "2010-2011 PERFORMANCE CATEGORY SCORE",
        "2010-2011 ENVIRONMENT GRADE",
        "SCHOOL",
        "PRINCIPAL"
    ],
    "landing_page": "https://data.cityofnewyork.us/d/yig9-9zum",
    "last_updated": "2014-09-05 17:37:49+00:00",
    "protocol": "https",
    "created": "2011-10-06 20:12:51+00:00"
}